pychoreographer/__init__.py
pychoreographer/pychoreographer.py
Pychoreographer-0.0.1.dist-info/LICENSE
Pychoreographer-0.0.1.dist-info/METADATA
Pychoreographer-0.0.1.dist-info/WHEEL
Pychoreographer-0.0.1.dist-info/entry_points.txt
Pychoreographer-0.0.1.dist-info/top_level.txt
Pychoreographer-0.0.1.dist-info/RECORD
