Metadata-Version: 2.1
Name: Pychoreographer
Version: 0.0.1
Summary: A customizable Python library for automating file operations, system monitoring, and routine tasks.
Author-email: Rajaa Lebchiri <rajaa.lebchiri@gmail.com>
Project-URL: Homepage, https://github.com/rajaalebchiri/pychoreographer
Project-URL: Issues, https://github.com/rajaalebchiri/pychoreographer/issues
Classifier: Programming Language :: Python :: 3
Classifier: License :: OSI Approved :: MIT License
Classifier: Operating System :: OS Independent
Requires-Python: >=3.8
License-File: LICENSE
